<annotation>
	<folder>autorickshaw - Google Search</folder>
	<filename>large.jpg</filename>
	<path>C:\Users\vikas\Documents\Bulk Image Downloader\autorickshaw - Google Search\large.jpg</path>
	<source>
		<database>Unknown</database>
	</source>
	<size>
		<width>960</width>
		<height>617</height>
		<depth>3</depth>
	</size>
	<segmented>0</segmented>
	<object>
		<name>auto</name>
		<pose>Unspecified</pose>
		<truncated>0</truncated>
		<difficult>0</difficult>
		<bndbox>
			<xmin>94</xmin>
			<ymin>42</ymin>
			<xmax>912</xmax>
			<ymax>566</ymax>
		</bndbox>
	</object>
</annotation>
